{
    "ptr_offset": null,
    "content": {
        "pallete": [
            {
                "offset": 0,
                "size": 1024
            }
        ],
        "map": null,
        "pixel": [
            {
                "format": "-pspindex8",
                "offset": 6144,
                "size": 6144,
                "width": 512,
                "height": 272,
                "chunk": 4,
                "chunk_offset": [
                    32,
                    15168,
                    27952,
                    40720,
                    53712
                ],
                "gzip_csizes": [
                    15120,
                    12768,
                    12752,
                    12976
                ],
                "gzip_dsizes": [
                    34816,
                    34816,
                    34816,
                    34816
                ]
            }
        ]
    }
}