{
    "ptr_offset": null,
    "content": {
        "pallete": [
            {
                "offset": 0,
                "size": 1024
            }
        ],
        "map": null,
        "pixel": [
            {
                "format": "-pspindex8",
                "offset": 6144,
                "size": 6144,
                "width": 512,
                "height": 272,
                "chunk": 4,
                "chunk_offset": [
                    32,
                    4720,
                    11776,
                    20352,
                    29920
                ],
                "gzip_csizes": [
                    4672,
                    7040,
                    8560,
                    9552
                ],
                "gzip_dsizes": [
                    34816,
                    34816,
                    34816,
                    34816
                ]
            }
        ]
    }
}