{
    "ptr_offset": null,
    "content": {
        "pallete": [
            {
                "offset": 0,
                "size": 1024
            }
        ],
        "map": null,
        "pixel": [
            {
                "format": "-pspindex8",
                "offset": 6144,
                "size": 6144,
                "width": 512,
                "height": 272,
                "chunk": 4,
                "chunk_offset": [
                    32,
                    12992,
                    25136,
                    42336,
                    59264
                ],
                "gzip_csizes": [
                    12944,
                    12128,
                    17184,
                    16912
                ],
                "gzip_dsizes": [
                    34816,
                    34816,
                    34816,
                    34816
                ]
            }
        ]
    }
}