{
    "ptr_offset": null,
    "content": {
        "pallete": [
            {
                "offset": 0,
                "size": 1024
            }
        ],
        "map": {
            "offset": 1024,
            "size": 5120
        },
        "pixel": [
            {
                "format": "-pspindex8",
                "offset": 6144,
                "size": 6144,
                "width": 512,
                "height": 160,
                "chunk": 3,
                "chunk_offset": [
                    32,
                    10400,
                    20800,
                    25152
                ],
                "gzip_csizes": [
                    10352,
                    10384,
                    4336
                ],
                "gzip_dsizes": [
                    32768,
                    32768,
                    16384
                ]
            }
        ]
    }
}